imj/__init__.py
imj-1.1.3.dist-info/METADATA
imj-1.1.3.dist-info/WHEEL
imj-1.1.3.dist-info/top_level.txt
imj-1.1.3.dist-info/RECORD
